Workbook
Name Aporte: Calculadora!$D$22
Name Patrimonio: Calculadora!$D$25
Name QtdAnos: Calculadora!$D$23
Name RendCart: Calculadora!$D$16
Name Salario: Calculadora!$D$15
Name SugInv10: Calculadora!$D$19
Name SugInv20: Calculadora!$D$18
Name SugInv30: Calculadora!$D$17
Name TaxaMensal: Calculadora!$D$24

Sheet Calculadora
B14: Configurações
B15: Salario | D15: 45000
B16: Rendimento da Carteira | D16: 0.008
B17: Sugestão de investimento 30% | D17: =$D$15*30% -> 13500
B18: Sugestão de investimento 20% | D18: =$D$15*20% -> 9000
B19: Sugestão de investimento 10% | D19: =$D$15*10% -> 4500
B21: Investimento Mensal
B22: Quanto vou investir por mês | D22: 13500
B23: Quantos anos vou investir | D23: 2
B24: Taxa de rendimento mensal | D24: 0.0108
B25: Patrimônio acumulado | D25: =FV(TaxaMensal,QtdAnos*12,Aporte*-1) -> 367616.66
B26: Dividendos mensais | D26: =Patrimonio*RendCart -> 2940.9333
B28: Cenários | C28: Patrimônio | D28: Dividendos
B29: Investimento em 2 anos | C29: =FV($D$24,Apoio!G3*12,$D$22*-1) -> 367616.66 | D29: =C29*RendCart -> 2940.9333
B30: Investimento em 5 anos | C30: =FV($D$24,Apoio!G4*12,$D$22*-1) -> 1131354.3 | D30: =C30*RendCart -> 9050.8341
B31: Investimento em 10 anos | C31: =FV($D$24,Apoio!G5*12,$D$22*-1) -> 3286678.5 | D31: =C31*RendCart -> 26293.428
B32: Investimento em 20 anos | C32: =FV($D$24,Apoio!G6*12,$D$22*-1) -> 15215161 | D32: =C32*RendCart -> 121721.29
B33: Investimento em 30 anos | C33: =FV($D$24,Apoio!G7*12,$D$22*-1) -> 58507715 | D33: =C33*RendCart -> 468061.72
B35: Perfil | C35: Moderado
B36: Valor a ser investido por mês | C36: =Aporte -> 13500
B37: Tipo de FII | C37: Percentual sugerido | D37: Valores
B38: Papel | C38: =VLOOKUP($C$35&"-"&B38,Apoio!B2:E20,4,FALSE) -> 0.32 | D38: =C38*$C$36 -> 4320
B39: Tijolo | C39: =VLOOKUP($C$35&"-"&B39,Apoio!B3:E21,4,FALSE) -> 0.35 | D39: =C39*$C$36 -> 4725
B40: Híbrido | C40: =VLOOKUP($C$35&"-"&B40,Apoio!B4:E22,4,FALSE) -> 0.08 | D40: =C40*$C$36 -> 1080
B41: FOFs | C41: =VLOOKUP($C$35&"-"&B41,Apoio!B5:E23,4,FALSE) -> 0.05 | D41: =C41*$C$36 -> 675
B42: Desenvolvimento | C42: =VLOOKUP($C$35&"-"&B42,Apoio!B6:E24,4,FALSE) -> 0.1 | D42: =C42*$C$36 -> 1350
B43: Hotelarias | C43: =VLOOKUP($C$35&"-"&B43,Apoio!B7:E25,4,FALSE) -> 0.1 | D43: =C43*$C$36 -> 1350
D44: =SUM(D38:D43) -> 13500

Sheet Apoio
B2: Chave | C2: Perfil | D2: Tipo de FII | E2: % | G2: Cenarios
B3: =C3&"-"&D3 -> Conservador-Papel | C3: Conservador | D3: Papel | E3: 0.3 | G3: 2
B4: =C4&"-"&D4 -> Conservador-Tijolo | C4: Conservador | D4: Tijolo | E4: 0.5 | G4: 5
B5: =C5&"-"&D5 -> Conservador-Híbrido | C5: Conservador | D5: Híbrido | E5: 0.1 | G5: 10
B6: =C6&"-"&D6 -> Conservador-FOFs | C6: Conservador | D6: FOFs | E6: 0.1 | G6: 20
B7: =C7&"-"&D7 -> Conservador-Desenvolvimento | C7: Conservador | D7: Desenvolvimento | E7: 0 | G7: 30
B8: =C8&"-"&D8 -> Conservador-Hotelarias | C8: Conservador | D8: Hotelarias | E8: 0
B9: =C9&"-"&D9 -> Moderado-Papel | C9: Moderado | D9: Papel | E9: 0.32
B10: =C10&"-"&D10 -> Moderado-Tijolo | C10: Moderado | D10: Tijolo | E10: 0.35
B11: =C11&"-"&D11 -> Moderado-Híbrido | C11: Moderado | D11: Híbrido | E11: 0.08
B12: =C12&"-"&D12 -> Moderado-FOFs | C12: Moderado | D12: FOFs | E12: 0.05
B13: =C13&"-"&D13 -> Moderado-Desenvolvimento | C13: Moderado | D13: Desenvolvimento | E13: 0.1
B14: =C14&"-"&D14 -> Moderado-Hotelarias | C14: Moderado | D14: Hotelarias | E14: 0.1
B15: =C15&"-"&D15 -> Agressivo-Papel | C15: Agressivo | D15: Papel | E15: 0.5
B16: =C16&"-"&D16 -> Agressivo-Tijolo | C16: Agressivo | D16: Tijolo | E16: 0.1
B17: =C17&"-"&D17 -> Agressivo-Híbrido | C17: Agressivo | D17: Híbrido | E17: 0.05
B18: =C18&"-"&D18 -> Agressivo-FOFs | C18: Agressivo | D18: FOFs | E18: 0.05
B19: =C19&"-"&D19 -> Agressivo-Desenvolvimento | C19: Agressivo | D19: Desenvolvimento | E19: 0.2
B20: =C20&"-"&D20 -> Agressivo-Hotelarias | C20: Agressivo | D20: Hotelarias | E20: 0.1
